__init__.py
SimpleRule34/Rule34.py
SimpleRule34/__init__.py
SimpleRule34/exceptions.py
SimpleRule34/types.py
SimpleRule34/utils.py
simple_rule34-0.1.6.1.dist-info/licenses/LICENSE
simple_rule34-0.1.6.1.dist-info/METADATA
simple_rule34-0.1.6.1.dist-info/WHEEL
simple_rule34-0.1.6.1.dist-info/top_level.txt
simple_rule34-0.1.6.1.dist-info/RECORD
