Metadata-Version: 2.4
Name: simple_rule34
Version: 0.1.6.1
Summary: Simple api wrapper of rule34.xxx for python with asynchronous support
Author-email: StarMan12 <author@example.com>
Project-URL: Homepage, https://github.com/SyperAlexKomp/simple-rule34-api
Project-URL: Bug Tracker, https://github.com/SyperAlexKomp/simple-rule34-api/issues
Classifier: Programming Language :: Python :: 3
Classifier: License :: OSI Approved :: MIT License
Classifier: Operating System :: OS Independent
Requires-Python: >=3.9
License-File: LICENSE
Requires-Dist: aiohttp==3.8.4
Requires-Dist: aiosignal==1.3.1
Requires-Dist: alabaster==0.7.13
Requires-Dist: async-timeout==4.0.2
Requires-Dist: attrs==23.1.0
Requires-Dist: Babel==2.9.1
Requires-Dist: build==0.10.0
Requires-Dist: certifi==2023.5.7
Requires-Dist: charset-normalizer==3.2.0
Requires-Dist: colorama==0.4.6
Requires-Dist: docopt==0.6.2
Requires-Dist: docutils==0.18.1
Requires-Dist: frozenlist==1.4.0
Requires-Dist: idna==3.4
Requires-Dist: imagesize==1.4.1
Requires-Dist: importlib-metadata==6.8.0
Requires-Dist: Jinja2==3.1.2
Requires-Dist: MarkupSafe==2.1.3
Requires-Dist: multidict==6.0.4
Requires-Dist: packaging==23.1
Requires-Dist: pipreqs==0.4.13
Requires-Dist: Pygments==2.15.1
Requires-Dist: pyproject_hooks==1.0.0
Requires-Dist: requests==2.31.0
Requires-Dist: snowballstemmer==2.2.0
Requires-Dist: Sphinx==6.2.1
Requires-Dist: sphinx-rtd-theme==1.2.2
Requires-Dist: sphinxcontrib-applehelp==1.0.4
Requires-Dist: sphinxcontrib-devhelp==1.0.2
Requires-Dist: sphinxcontrib-htmlhelp==2.0.1
Requires-Dist: sphinxcontrib-jquery==4.1
Requires-Dist: sphinxcontrib-jsmath==1.0.1
Requires-Dist: sphinxcontrib-qthelp==1.0.3
Requires-Dist: sphinxcontrib-serializinghtml==1.1.5
Requires-Dist: tomli==2.0.1
Requires-Dist: urllib3==2.0.3
Requires-Dist: yarg==0.1.9
Requires-Dist: yarl==1.9.2
Requires-Dist: zipp==3.16.2
Requires-Dist: aiofiles~=23.2.1
Requires-Dist: pydantic~=2.7.1
Dynamic: license-file
